{
    "version": "1.1",
    "type": "single",
    "name": "Leroy: Under Guard",
    "url": "https://genshin-impact.fandom.com/wiki/Leroy%3A_Under_Guard",
    "starting_location": {
        "text": "\u25c0Court of Fontaine: Vasari Passage\u25b6\u25c1https://genshin-impact.fandom.com/wiki/Court_of_Fontaine:_Vasari_Passage\u25b7 , \u25c0Fontaine\u25b6\u25c1https://genshin-impact.fandom.com/wiki/Fontaine\u25b7"
    },
    "requirements": null,
    "rewards": [
        {
            "Name": "Adventure EXP",
            "Value": "150",
            "Link": "https://genshin-impact.fandom.com/wiki/Adventure_EXP",
            "Image": "Item_Adventure_EXP.png",
            "Rarity": "3"
        },
        {
            "Name": "Primogem",
            "Value": "20",
            "Link": "https://genshin-impact.fandom.com/wiki/Primogem",
            "Image": "Item_Primogem.png",
            "Rarity": "5"
        },
        {
            "Name": "Mora",
            "Value": "25,000",
            "Link": "https://genshin-impact.fandom.com/wiki/Mora",
            "Image": "Item_Mora.png",
            "Rarity": "3"
        },
        {
            "Name": "Fruity Trio",
            "Value": "3",
            "Link": "https://genshin-impact.fandom.com/wiki/Fruity_Trio",
            "Image": "Item_Fruity_Trio.png",
            "Rarity": "3"
        }
    ],
    "steps": [
        {
            "tag": "ul",
            "steps": [
                {
                    "tag": "li",
                    "text": "The quest unlocks automatically 1 in-game day after completing \u25c0Leroy: Firing Squad\u25b6\u25c1https://genshin-impact.fandom.com/wiki/Leroy:_Firing_Squad\u25b7"
                }
            ]
        },
        {
            "tag": "ol",
            "steps": [
                {
                    "tag": "li",
                    "text": "Talk to Molli"
                },
                {
                    "tag": "li",
                    "text": "Clean around the house (0/2)"
                },
                {
                    "tag": "li",
                    "text": "Discuss with Molli"
                },
                {
                    "tag": "li",
                    "text": "Knock on the door"
                },
                {
                    "tag": "li",
                    "text": "Go to the side and talk with Paimon"
                }
            ]
        }
    ],
    "dialogue": true
}