{
    "version": "1.1",
    "type": "single",
    "name": "Mushounin",
    "url": "https://genshin-impact.fandom.com/wiki/Mushounin",
    "starting_location": {
        "text": "\u25c0Uyuu Restaurant\u25b6\u25c1https://genshin-impact.fandom.com/wiki/Uyuu_Restaurant\u25b7 , \u25c0Inazuma City\u25b6\u25c1https://genshin-impact.fandom.com/wiki/Inazuma_City\u25b7 , \u25c0Inazuma\u25b6\u25c1https://genshin-impact.fandom.com/wiki/Inazuma\u25b7"
    },
    "requirements": null,
    "rewards": [
        {
            "Name": "Adventure EXP",
            "Value": "300",
            "Link": "https://genshin-impact.fandom.com/wiki/Adventure_EXP",
            "Image": "Item_Adventure_EXP.png",
            "Rarity": "3"
        },
        {
            "Name": "Primogem",
            "Value": "40",
            "Link": "https://genshin-impact.fandom.com/wiki/Primogem",
            "Image": "Item_Primogem.png",
            "Rarity": "5"
        },
        {
            "Name": "Mora",
            "Value": "20,000",
            "Link": "https://genshin-impact.fandom.com/wiki/Mora",
            "Image": "Item_Mora.png",
            "Rarity": "3"
        },
        {
            "Name": "Hero's Wit",
            "Value": "3",
            "Link": "https://genshin-impact.fandom.com/wiki/Hero%27s_Wit",
            "Image": "Item_Hero%27s_Wit.png",
            "Rarity": "4"
        },
        {
            "Name": "Mystic Enhancement Ore",
            "Value": "3",
            "Link": "https://genshin-impact.fandom.com/wiki/Mystic_Enhancement_Ore",
            "Image": "Item_Mystic_Enhancement_Ore.png",
            "Rarity": "3"
        }
    ],
    "steps": [
        {
            "tag": "ol",
            "steps": [
                {
                    "tag": "li",
                    "text": "Look for the two performers and talk to them (0/2)"
                },
                {
                    "tag": "li",
                    "text": "Wait until evening (18:00 \u2013 20:00)"
                },
                {
                    "tag": "li",
                    "text": "Go to \u25c0Komore Teahouse\u25b6\u25c1https://genshin-impact.fandom.com/wiki/Komore_Teahouse\u25b7"
                },
                {
                    "tag": "li",
                    "text": "Talk to Xavier"
                },
                {
                    "tag": "li",
                    "text": "Talk to Xavier to begin the shoot"
                },
                {
                    "tag": "ul",
                    "steps": [
                        {
                            "tag": "li",
                            "text": "Choose the first option for all dialogues"
                        }
                    ]
                },
                {
                    "tag": "li",
                    "text": "Talk to Xavier"
                },
                {
                    "tag": "li",
                    "text": "Wait until evening (18:00 \u2013 20:00)"
                },
                {
                    "tag": "li",
                    "text": "Go to \u25c0Nazuchi Beach\u25b6\u25c1https://genshin-impact.fandom.com/wiki/Nazuchi_Beach\u25b7"
                },
                {
                    "tag": "li",
                    "text": "Persuade the extras"
                },
                {
                    "tag": "ul",
                    "steps": [
                        {
                            "tag": "li",
                            "text": "<img:kairagi_fiery_might> \u25c0Kairagi: Fiery Might\u25b6\u25c1https://genshin-impact.fandom.com/wiki/Kairagi:_Fiery_Might\u25b7 \u00d71",
                            "img": {
                                "kairagi_fiery_might": "Kairagi_Fiery_Might_Icon.png"
                            }
                        },
                        {
                            "tag": "li",
                            "text": "<img:nobushi_hitsukeban> \u25c0Nobushi: Hitsukeban\u25b6\u25c1https://genshin-impact.fandom.com/wiki/Nobushi:_Hitsukeban\u25b7 \u00d71",
                            "img": {
                                "nobushi_hitsukeban": "Nobushi_Hitsukeban_Icon.png"
                            }
                        },
                        {
                            "tag": "li",
                            "text": "<img:nobushi_jintouban> \u25c0Nobushi: Jintouban\u25b6\u25c1https://genshin-impact.fandom.com/wiki/Nobushi:_Jintouban\u25b7 \u00d71",
                            "img": {
                                "nobushi_jintouban": "Nobushi_Jintouban_Icon.png"
                            }
                        }
                    ]
                },
                {
                    "tag": "li",
                    "text": "Talk to Xavier"
                },
                {
                    "tag": "li",
                    "text": "Talk to Xavier to begin the shoot"
                },
                {
                    "tag": "ul",
                    "steps": [
                        {
                            "tag": "li",
                            "text": "Do not leave the recording area of the Film Kamera"
                        },
                        {
                            "tag": "li",
                            "text": "\"Bandits\" Defeated 0/3"
                        },
                        {
                            "tag": "li",
                            "text": "Change positions 0/3"
                        }
                    ]
                },
                {
                    "tag": "ul",
                    "steps": [
                        {
                            "tag": "li",
                            "text": "<img:kairagi_fiery_might> \u25c0Yamada Hifumi\u25b6\u25c1https://genshin-impact.fandom.com/wiki/Kairagi:_Fiery_Might\u25b7 \u00d71",
                            "img": {
                                "kairagi_fiery_might": "Kairagi_Fiery_Might_Icon.png"
                            }
                        },
                        {
                            "tag": "li",
                            "text": "<img:nobushi_hitsukeban> \u25c0Nobushi: Hitsukeban\u25b6\u25c1https://genshin-impact.fandom.com/wiki/Nobushi:_Hitsukeban\u25b7 \u00d71",
                            "img": {
                                "nobushi_hitsukeban": "Nobushi_Hitsukeban_Icon.png"
                            }
                        },
                        {
                            "tag": "li",
                            "text": "<img:nobushi_jintouban> \u25c0Nobushi: Jintouban\u25b6\u25c1https://genshin-impact.fandom.com/wiki/Nobushi:_Jintouban\u25b7 \u00d71",
                            "img": {
                                "nobushi_jintouban": "Nobushi_Jintouban_Icon.png"
                            }
                        }
                    ]
                },
                {
                    "tag": "li",
                    "text": "Wait until the following evening (18:00 \u2013 20:00)"
                },
                {
                    "tag": "li",
                    "text": "Head to the designated location"
                },
                {
                    "tag": "li",
                    "text": "Talk to Xavier"
                },
                {
                    "tag": "li",
                    "text": "Talk to Xavier to begin the shoot"
                },
                {
                    "tag": "ul",
                    "steps": [
                        {
                            "tag": "li",
                            "text": "Choose the first options for all dialogues."
                        },
                        {
                            "tag": "li",
                            "text": "Do not leave the recording area of the Film Kamera"
                        },
                        {
                            "tag": "li",
                            "text": "Samurai Defeated 0/1"
                        }
                    ]
                },
                {
                    "tag": "ul",
                    "steps": [
                        {
                            "tag": "li",
                            "text": "<img:shogunate_infantry> \u25c0Wakayama Kojuurou\u25b6\u25c1https://genshin-impact.fandom.com/wiki/Shogunate_Infantry\u25b7",
                            "img": {
                                "shogunate_infantry": "Shogunate_Infantry_Icon.png"
                            }
                        }
                    ]
                },
                {
                    "tag": "li",
                    "text": "Rendezvous with everyone"
                }
            ]
        }
    ],
    "dialogue": true
}